LICENSE.md
MANIFEST.in
README.md
setup.cfg
setup.py
drf_safe_jack.egg-info/PKG-INFO
drf_safe_jack.egg-info/SOURCES.txt
drf_safe_jack.egg-info/dependency_links.txt
drf_safe_jack.egg-info/not-zip-safe
drf_safe_jack.egg-info/top_level.txt
rest_framework/__init__.py
rest_framework/apps.py
rest_framework/authentication.py
rest_framework/checks.py
rest_framework/compat.py
rest_framework/decorators.py
rest_framework/documentation.py
rest_framework/exceptions.py
rest_framework/fields.py
rest_framework/filters.py
rest_framework/generics.py
rest_framework/metadata.py
rest_framework/mixins.py
rest_framework/negotiation.py
rest_framework/pagination.py
rest_framework/parsers.py
rest_framework/permissions.py
rest_framework/relations.py
rest_framework/renderers.py
rest_framework/request.py
rest_framework/response.py
rest_framework/reverse.py
rest_framework/routers.py
rest_framework/serializers.py
rest_framework/settings.py
rest_framework/status.py
rest_framework/test.py
rest_framework/throttling.py
rest_framework/urlpatterns.py
rest_framework/urls.py
rest_framework/validators.py
rest_framework/versioning.py
rest_framework/views.py
rest_framework/viewsets.py
rest_framework/authtoken/__init__.py
rest_framework/authtoken/admin.py
rest_framework/authtoken/apps.py
rest_framework/authtoken/models.py
rest_framework/authtoken/serializers.py
rest_framework/authtoken/views.py
rest_framework/authtoken/management/__init__.py
rest_framework/authtoken/management/commands/__init__.py
rest_framework/authtoken/management/commands/drf_create_token.py
rest_framework/authtoken/migrations/0001_initial.py
rest_framework/authtoken/migrations/0002_auto_20160226_1747.py
rest_framework/authtoken/migrations/__init__.py
rest_framework/locale/ach/LC_MESSAGES/django.mo
rest_framework/locale/ar/LC_MESSAGES/django.mo
rest_framework/locale/be/LC_MESSAGES/django.mo
rest_framework/locale/ca/LC_MESSAGES/django.mo
rest_framework/locale/ca_ES/LC_MESSAGES/django.mo
rest_framework/locale/cs/LC_MESSAGES/django.mo
rest_framework/locale/da/LC_MESSAGES/django.mo
rest_framework/locale/de/LC_MESSAGES/django.mo
rest_framework/locale/el/LC_MESSAGES/django.mo
rest_framework/locale/el_GR/LC_MESSAGES/django.mo
